textual_dev/__init__.py
textual_dev/__main__.py
textual_dev/cli.py
textual_dev/client.py
textual_dev/previews/__init__.py
textual_dev/previews/borders.py
textual_dev/previews/colors.css
textual_dev/previews/colors.py
textual_dev/previews/easing.css
textual_dev/previews/easing.py
textual_dev/previews/keys.py
textual_dev/py.typed
textual_dev/redirect_output.py
textual_dev/renderables.py
textual_dev/server.py
textual_dev/service.py
textual_dev/tools/diagnose.py
textual_dev/tools/run.py
textual_dev-1.6.0.dist-info/LICENSE
textual_dev-1.6.0.dist-info/METADATA
textual_dev-1.6.0.dist-info/WHEEL
textual_dev-1.6.0.dist-info/entry_points.txt
textual_dev-1.6.0.dist-info/RECORD
